visualeda/__init__.py
visualeda-0.4.dist-info/LICENCE.txt
visualeda-0.4.dist-info/METADATA
visualeda-0.4.dist-info/WHEEL
visualeda-0.4.dist-info/top_level.txt
visualeda-0.4.dist-info/RECORD
